Metadata-Version: 2.1
Name: fernet-cli
Version: 0.0.2
Summary: A CLI to manipulate fernet encrypted secrets
Home-page: https://github.com/drivy/fernet-cli
Author: Getaround
License: MIT
Project-URL: Homepage, https://github.com/drivy/fernet-cli
Project-URL: Bug Tracker, https://github.com/drivy/fernet-cli/issues
Platform: UNKNOWN
Classifier: Operating System :: OS Independent
Classifier: Programming Language :: Python
Classifier: Programming Language :: Python :: 3
Classifier: Environment :: Console
Classifier: Intended Audience :: Developers
Classifier: License :: OSI Approved :: MIT License
Requires-Python: >=3.6
License-File: LICENSE
